ws3/__init__.py
ws3/common.py
ws3/core.py
ws3/financial.py
ws3/forest.py
ws3/forest_helper.py
ws3/opt.py
ws3/spatial.py
ws3-1.0.5.dist-info/METADATA
ws3-1.0.5.dist-info/WHEEL
ws3-1.0.5.dist-info/licenses/LICENSE
ws3-1.0.5.dist-info/RECORD
