Metadata-Version: 2.4
Name: ws3
Version: 1.0.5
Summary: A Python framework for forest estate modeling and wood supply simulation
Author-email: Gregory Paradis <gregory.paradis@ubc.ca>
Maintainer-email: Kathleen Coupland <kathleen.coupland@ubc.ca>, Elaheh Ghasemi <elaheh.ghasemi@ubc.ca>, Salar Ghotb <salar.ghotb@ubc.ca>
License: MIT
License-File: LICENSE
Requires-Python: >=3.9
Requires-Dist: dill
Requires-Dist: fiona
Requires-Dist: highspy
Requires-Dist: matplotlib
Requires-Dist: numpy>=1.21
Requires-Dist: pandas>=1.3
Requires-Dist: profilehooks
Requires-Dist: rasterio
Requires-Dist: scipy>=1.7
Provides-Extra: cbm
Requires-Dist: libcbm; extra == 'cbm'
Provides-Extra: gurobi
Requires-Dist: gurobipy; extra == 'gurobi'
Provides-Extra: pulp
Requires-Dist: pulp; extra == 'pulp'
